talert/__init__.py
talert/bot.py
talert/core.py
talert/auth/__init__.py
talert-0.1.4.dist-info/LICENSE
talert-0.1.4.dist-info/METADATA
talert-0.1.4.dist-info/WHEEL
talert-0.1.4.dist-info/top_level.txt
talert-0.1.4.dist-info/RECORD
